eeg_blinks/__init__.py
eeg_blinks/default_setting.py
eeg_blinks/pyblinker.py
eeg_blinks/utilities/__init__.py
eeg_blinks/utilities/extractBlinkProperties.py
eeg_blinks/utilities/fit_blink.py
eeg_blinks/utilities/getCandidateSignal.py
eeg_blinks/utilities/misc.py
eeg_blinks/utilities/zero_crossing.py
eeg_blinks/vislab/__init__.py
eeg_blinks/vislab/base_left_right.py
eeg_blinks/vislab/blink_posi_vislab.py
eeg_blinks/vislab/getBlinkPositions_vislab.py
eeg_blinks/viz/__init__.py
eeg_blinks/viz/viz_pd.py
eeg_blinks/viz/viz_sanity.py
eeg_blinks-0.0.5.dist-info/METADATA
eeg_blinks-0.0.5.dist-info/WHEEL
eeg_blinks-0.0.5.dist-info/top_level.txt
eeg_blinks-0.0.5.dist-info/RECORD
