Metadata-Version: 2.1
Name: eeg-blinks
Version: 0.0.5
Summary: make life easier
Author: rpb
Requires-Dist: seaborn
